pyonir/__init__.py
pyonir/cli.py
pyonir/pyonir_types.py
pyonir/core/__init__.py
pyonir/core/app.py
pyonir/core/auth.py
pyonir/core/database.py
pyonir/core/generators.py
pyonir/core/loaders.py
pyonir/core/mapper.py
pyonir/core/media.py
pyonir/core/page.py
pyonir/core/parser.py
pyonir/core/schemas.py
pyonir/core/server.py
pyonir/core/services.py
pyonir/core/templating.py
pyonir/core/user.py
pyonir/core/utils.py
pyonir/docs/file-base-routing-setup.md
pyonir/docs/frontend-setup.md
pyonir/docs/plugin-setup.md
pyonir/docs/routing-setup.md
pyonir/libs/__init__.py
pyonir/libs/app_setup/.env.example
pyonir/libs/app_setup/README.md
pyonir/libs/app_setup/main.py
pyonir/libs/app_setup/requirements.txt
pyonir/libs/app_setup/backend/README.md
pyonir/libs/app_setup/backend/__init__.py
pyonir/libs/app_setup/backend/pages/sample.py
pyonir/libs/app_setup/contents/api/docs.md
pyonir/libs/app_setup/contents/configs/app.md
pyonir/libs/app_setup/contents/pages/.virtual_routes.md
pyonir/libs/app_setup/contents/pages/demo.md
pyonir/libs/app_setup/contents/pages/index.md
pyonir/libs/app_setup/frontend/README.md
pyonir/libs/app_setup/frontend/public/city-gemini.png
pyonir/libs/app_setup/frontend/themes/pencil/README.md
pyonir/libs/app_setup/frontend/themes/pencil/static/favicon.ico
pyonir/libs/app_setup/frontend/themes/pencil/static/css/button.css
pyonir/libs/app_setup/frontend/themes/pencil/static/css/forms.css
pyonir/libs/app_setup/frontend/themes/pencil/static/css/grid.css
pyonir/libs/app_setup/frontend/themes/pencil/static/css/menus.css
pyonir/libs/app_setup/frontend/themes/pencil/static/css/pencil.css
pyonir/libs/app_setup/frontend/themes/pencil/static/css/props.css
pyonir/libs/app_setup/frontend/themes/pencil/static/css/recommendation-card.css
pyonir/libs/app_setup/frontend/themes/pencil/static/css/reset.css
pyonir/libs/app_setup/frontend/themes/pencil/static/css/table.css
pyonir/libs/app_setup/frontend/themes/pencil/static/css/typography.css
pyonir-0.0.54.dist-info/licenses/LICENSE.md
pyonir-0.0.54.dist-info/METADATA
pyonir-0.0.54.dist-info/WHEEL
pyonir-0.0.54.dist-info/entry_points.txt
pyonir-0.0.54.dist-info/top_level.txt
pyonir-0.0.54.dist-info/RECORD
