Metadata-Version: 2.4
Name: pyonir
Version: 0.0.54
Summary: a python library for building web applications
Author-email: Derry Spann <pyonir@derryspann.com>
License: BSD-3-Clause
Project-URL: Homepage, https://pyonir.dev
Requires-Python: >=3.9
License-File: LICENSE.md
Requires-Dist: starlette
Requires-Dist: uvicorn
Requires-Dist: starlette_session
Requires-Dist: starlette_wtf
Requires-Dist: pytz
Requires-Dist: sortedcontainers
Requires-Dist: jinja2
Requires-Dist: webassets
Requires-Dist: argon2-cffi
Requires-Dist: PyJWT
Requires-Dist: requests
Requires-Dist: mistletoe
Requires-Dist: sqlmodel
Requires-Dist: pymediainfo
Requires-Dist: pillow
Dynamic: license-file
